eminem_lyric/__init__.py
eminem_lyric/eminem_lyric.py
tests/__init__.py
tests/test_eminem_lyric.py
eminem_lyric-1.0.8.dist-info/LICENSE
eminem_lyric-1.0.8.dist-info/METADATA
eminem_lyric-1.0.8.dist-info/WHEEL
eminem_lyric-1.0.8.dist-info/top_level.txt
eminem_lyric-1.0.8.dist-info/RECORD
