Metadata-Version: 2.1
Name: eminem_lyric
Version: 1.0.8
Summary: A Python package for fetching Eminem song lyrics.
Home-page: https://github.com/emads22/eminem-lyric-package
Author: Emad
Author-email: emadsaab222@gmail.com
License: MIT
Keywords: eminem,lyric,lyrics,eminemlyric,eminem_lyric,stan,slim shady,api
Classifier: License :: OSI Approved :: MIT License
Classifier: Operating System :: OS Independent
Classifier: Programming Language :: Python :: 3.7
Classifier: Programming Language :: Python :: 3.8
Classifier: Programming Language :: Python :: 3.9
Classifier: Programming Language :: Python :: 3.10
Classifier: Programming Language :: Python :: 3.11
Classifier: Programming Language :: Python :: 3.12
Classifier: Development Status :: 5 - Production/Stable
Classifier: Intended Audience :: Developers
Classifier: Intended Audience :: Information Technology
Classifier: Intended Audience :: End Users/Desktop
Classifier: Topic :: Software Development
Classifier: Topic :: Multimedia :: Sound/Audio
Classifier: Topic :: Text Processing :: Linguistic
Classifier: Topic :: Utilities
License-File: LICENSE
Requires-Dist: requests
